vizel/__init__.py
vizel/cli.py
vizel-0.3.0.dist-info/entry_points.txt
vizel-0.3.0.dist-info/LICENSE
vizel-0.3.0.dist-info/WHEEL
vizel-0.3.0.dist-info/METADATA
vizel-0.3.0.dist-info/RECORD
