Metadata-Version: 2.1
Name: vizel
Version: 0.3.0
Summary: Vizualise a Zettelkasten
Home-page: https://github.com/BasilPH/vizel
License: GPL-3.0-only
Keywords: zettelkasten,knowledge-management
Author: Basil Philipp
Author-email: basil@interdimensional-television.com
Requires-Python: >=2.7, !=3.0.*, !=3.1.*, !=3.2.*, !=3.3.*, !=3.4.*
Classifier: Environment :: Console
Classifier: License :: OSI Approved :: GNU General Public License v3 (GPLv3)
Classifier: Natural Language :: English
Classifier: Operating System :: OS Independent
Classifier: Programming Language :: Python :: 2
Classifier: Programming Language :: Python :: 2.7
Classifier: Programming Language :: Python :: 3
Classifier: Programming Language :: Python :: 3.5
Classifier: Programming Language :: Python :: 3.6
Classifier: Programming Language :: Python :: 3.7
Classifier: Programming Language :: Python :: 3.8
Classifier: Topic :: Text Processing
Classifier: Topic :: Utilities
Requires-Dist: click (>=7.1.1,<8.0.0)
Requires-Dist: graphviz (>=0.13.2,<0.14.0)
Requires-Dist: networkx (==2.2); python_version >= "2.7" and python_version < "3.0"
Requires-Dist: networkx (==2.4); python_version >= "3.5" and python_version < "4.0"
Requires-Dist: six (>=1.14.0,<2.0.0)
Project-URL: Repository, https://github.com/BasilPH/vizel
